[{
    "name": "Github",
    "icon": "/images/icon/github.png",
    "tip": "去 Github 看看",
    "url": "https://github.com/lswlc33"
}, {
    "name": "BiliBili",
    "icon": "/images/icon/bilibili.png",
    "tip": "(゜-゜)つロ 干杯 ~",
    "url": "https://space.bilibili.com/275618785"
}, {
    "name": "QQ",
    "icon": "/images/icon/qq.png",
    "tip": "可这是QQ邮箱",
    "url": "mailto:lswlc33@qq.com"
}, {
    "name": "Email",
    "icon": "/images/icon/email.png",
    "tip": "你说得对，我有两个邮箱",
    "url": "mailto:lswlc33@outlook.com"
}, {
    "name": "Twitter",
    "icon": "/images/icon/twitter.png",
    "tip": "是小鲨鱼的推 ~",
    "url": "https://twitter.com/gawrgura"
}, {
    "name": "Telegram",
    "icon": "/images/icon/telegram.png",
    "tip": "你懂的 ~",
    "url": "https://t.me/cai_xu_ikun"
}]